dooders/__init__.py
dooders/benchmark.py
dooders/experiment.py
dooders/investigate.py
dooders/animations/__init__.py
dooders/animations/animate.py
dooders/animations/move_history.py
dooders/charts/__init__.py
dooders/charts/accuracy.py
dooders/charts/boxplot.py
dooders/charts/evolution_speed.py
dooders/charts/fit_count_and_accuracy.py
dooders/charts/functions.py
dooders/charts/gene_embedding.py
dooders/charts/generation_spread.py
dooders/charts/grid.py
dooders/charts/histogram.py
dooders/charts/perception_state.py
dooders/data/__init__.py
dooders/data/data.py
dooders/data/dooder_dataframe.py
dooders/data/experiment_results.py
dooders/data/gene_embedding_dataframe.py
dooders/data/inference_record_dataframe.py
dooders/data/schema.py
dooders/experiments/__init__.py
dooders/experiments/base.py
dooders/experiments/recursive_artificial_selection.py
dooders/reports/__init__.py
dooders/reports/base.py
dooders/reports/recursive_artificial_selection.py
dooders/sdk/__init__.py
dooders/sdk/config.py
dooders/sdk/simulation.py
dooders/sdk/actions/__init__.py
dooders/sdk/actions/consume.py
dooders/sdk/actions/move.py
dooders/sdk/actions/reproduce.py
dooders/sdk/base/__init__.py
dooders/sdk/base/agent.py
dooders/sdk/base/base_core.py
dooders/sdk/base/base_policy.py
dooders/sdk/base/base_time.py
dooders/sdk/base/reality.py
dooders/sdk/conditions/__init__.py
dooders/sdk/conditions/death.py
dooders/sdk/conditions/reproduction.py
dooders/sdk/conditions/stop.py
dooders/sdk/core/__init__.py
dooders/sdk/core/action.py
dooders/sdk/core/assemble.py
dooders/sdk/core/circuit.py
dooders/sdk/core/condition.py
dooders/sdk/core/configure.py
dooders/sdk/core/core.py
dooders/sdk/core/default_settings.py
dooders/sdk/core/fate.py
dooders/sdk/core/model.py
dooders/sdk/core/policy.py
dooders/sdk/core/settings.py
dooders/sdk/core/step.py
dooders/sdk/core/strategy.py
dooders/sdk/core/surface.py
dooders/sdk/core/variables.py
dooders/sdk/learning/__init__.py
dooders/sdk/learning/learning.py
Dooders-1.3.0.dist-info/LICENSE.md
Dooders-1.3.0.dist-info/METADATA
Dooders-1.3.0.dist-info/WHEEL
Dooders-1.3.0.dist-info/top_level.txt
Dooders-1.3.0.dist-info/RECORD
