Metadata-Version: 2.1
Name: Dooders
Version: 1.3.0
Summary: Dooders is an open-source research project focused on the 
Home-page: https://github.com/csmangum/Dooders
Download-URL: https://github.com/csmangum/Dooders/archive/refs/tags/v0.3.0.tar.gz
Author: Chris Mangum
Author-email: csmangum@gmail.com
License: MIT
Keywords: Artificial Intelligence,Simulation,AI Agents,Cognitive Agents,Evolutionary Algorithms,Emergent Behavior,Open-Source,Research Project,Digital Environment,Machine Learning,Agent-Based Model,Reinforcement Learning,AI Environment,Causal Control,Energy Consumption,Autonomous Agents,AI Development,Virtual Reality,Simulated Reality,AI Research,Computational Intelligence,Interactive Simulation,AI Evolution,Complex Systems,Life Simulation
Classifier: Development Status :: 3 - Alpha
Classifier: Intended Audience :: Science/Research
Classifier: Topic :: Scientific/Engineering :: Artificial Intelligence
Classifier: License :: OSI Approved :: MIT License
Classifier: Natural Language :: English
Classifier: Programming Language :: Python :: 3
Classifier: Programming Language :: Python :: 3 :: Only
Classifier: Operating System :: OS Independent
License-File: LICENSE.md
Requires-Dist: fastapi
Requires-Dist: imageio
Requires-Dist: matplotlib
Requires-Dist: networkx
Requires-Dist: pandas
Requires-Dist: Pillow
Requires-Dist: plotly
Requires-Dist: psycopg2-binary
Requires-Dist: pydantic
Requires-Dist: pygame
Requires-Dist: pytest
Requires-Dist: python-dotenv
Requires-Dist: pyyaml
Requires-Dist: scikit-learn
Requires-Dist: scipy
Requires-Dist: tqdm
Requires-Dist: structlog
